[
  {
    "timestamp": "2026-06-30 08:21:21",
    "ticker": "QQQ",
    "decision": "esperar confirmación",
    "decisionLabel": "🟡 Esperar confirmación",
    "score": 53.0,
    "semaforo": "🟡 Riesgo medio",
    "precio": 724.02,
    "shortStrike": 733,
    "longStrike": 734.0,
    "vwap": 718.0,
    "regimen": "Trend Alcista",
    "tramo": "Premarket"
  },
  {
    "timestamp": "2026-06-30 08:22:24",
    "ticker": "QQQ",
    "decision": "esperar confirmación",
    "decisionLabel": "🟡 Esperar confirmación",
    "score": 53.0,
    "semaforo": "🟡 Riesgo medio",
    "precio": 724.02,
    "shortStrike": 733,
    "longStrike": 734.0,
    "vwap": 718.0,
    "regimen": "Trend Alcista",
    "tramo": "Premarket"
  },
  {
    "timestamp": "2026-06-30 08:23:27",
    "ticker": "QQQ",
    "decision": "esperar confirmación",
    "decisionLabel": "🟡 Esperar confirmación",
    "score": 53.0,
    "semaforo": "🟡 Riesgo medio",
    "precio": 724.02,
    "shortStrike": 733,
    "longStrike": 734.0,
    "vwap": 718.0,
    "regimen": "Trend Alcista",
    "tramo": "Premarket"
  },
  {
    "timestamp": "2026-06-30 08:24:30",
    "ticker": "QQQ",
    "decision": "esperar confirmación",
    "decisionLabel": "🟡 Esperar confirmación",
    "score": 53.0,
    "semaforo": "🟡 Riesgo medio",
    "precio": 724.02,
    "shortStrike": 733,
    "longStrike": 734.0,
    "vwap": 718.0,
    "regimen": "Trend Alcista",
    "tramo": "Premarket"
  },
  {
    "timestamp": "2026-06-30 08:25:33",
    "ticker": "QQQ",
    "decision": "esperar confirmación",
    "decisionLabel": "🟡 Esperar confirmación",
    "score": 53.0,
    "semaforo": "🟡 Riesgo medio",
    "precio": 724.02,
    "shortStrike": 733,
    "longStrike": 734.0,
    "vwap": 718.0,
    "regimen": "Trend Alcista",
    "tramo": "Premarket"
  },
  {
    "timestamp": "2026-06-30 08:26:36",
    "ticker": "QQQ",
    "decision": "esperar confirmación",
    "decisionLabel": "🟡 Esperar confirmación",
    "score": 53.0,
    "semaforo": "🟡 Riesgo medio",
    "precio": 724.02,
    "shortStrike": 733,
    "longStrike": 734.0,
    "vwap": 718.0,
    "regimen": "Trend Alcista",
    "tramo": "Premarket"
  },
  {
    "timestamp": "2026-06-30 08:27:39",
    "ticker": "QQQ",
    "decision": "esperar confirmación",
    "decisionLabel": "🟡 Esperar confirmación",
    "score": 53.0,
    "semaforo": "🟡 Riesgo medio",
    "precio": 724.02,
    "shortStrike": 733,
    "longStrike": 734.0,
    "vwap": 718.0,
    "regimen": "Trend Alcista",
    "tramo": "Premarket"
  },
  {
    "timestamp": "2026-06-30 08:28:42",
    "ticker": "QQQ",
    "decision": "esperar confirmación",
    "decisionLabel": "🟡 Esperar confirmación",
    "score": 53.0,
    "semaforo": "🟡 Riesgo medio",
    "precio": 724.02,
    "shortStrike": 733,
    "longStrike": 734.0,
    "vwap": 718.0,
    "regimen": "Trend Alcista",
    "tramo": "Premarket"
  },
  {
    "timestamp": "2026-06-30 08:29:45",
    "ticker": "QQQ",
    "decision": "esperar confirmación",
    "decisionLabel": "🟡 Esperar confirmación",
    "score": 53.0,
    "semaforo": "🟡 Riesgo medio",
    "precio": 724.02,
    "shortStrike": 733,
    "longStrike": 734.0,
    "vwap": 718.0,
    "regimen": "Trend Alcista",
    "tramo": "Premarket"
  },
  {
    "timestamp": "2026-06-30 08:30:48",
    "ticker": "QQQ",
    "decision": "esperar confirmación",
    "decisionLabel": "🟡 Esperar confirmación",
    "score": 53.0,
    "semaforo": "🟡 Riesgo medio",
    "precio": 724.02,
    "shortStrike": 733,
    "longStrike": 734.0,
    "vwap": 718.0,
    "regimen": "Trend Alcista",
    "tramo": "Premarket"
  },
  {
    "timestamp": "2026-06-30 08:31:52",
    "ticker": "QQQ",
    "decision": "esperar confirmación",
    "decisionLabel": "🟡 Esperar confirmación",
    "score": 53.0,
    "semaforo": "🟡 Riesgo medio",
    "precio": 724.02,
    "shortStrike": 733,
    "longStrike": 734.0,
    "vwap": 718.0,
    "regimen": "Trend Alcista",
    "tramo": "Premarket"
  },
  {
    "timestamp": "2026-06-30 08:32:55",
    "ticker": "QQQ",
    "decision": "esperar confirmación",
    "decisionLabel": "🟡 Esperar confirmación",
    "score": 53.0,
    "semaforo": "🟡 Riesgo medio",
    "precio": 724.02,
    "shortStrike": 733,
    "longStrike": 734.0,
    "vwap": 718.0,
    "regimen": "Trend Alcista",
    "tramo": "Premarket"
  },
  {
    "timestamp": "2026-06-30 08:33:59",
    "ticker": "QQQ",
    "decision": "esperar confirmación",
    "decisionLabel": "🟡 Esperar confirmación",
    "score": 53.0,
    "semaforo": "🟡 Riesgo medio",
    "precio": 724.02,
    "shortStrike": 733,
    "longStrike": 734.0,
    "vwap": 718.0,
    "regimen": "Trend Alcista",
    "tramo": "Premarket"
  },
  {
    "timestamp": "2026-06-30 08:35:02",
    "ticker": "QQQ",
    "decision": "esperar confirmación",
    "decisionLabel": "🟡 Esperar confirmación",
    "score": 53.0,
    "semaforo": "🟡 Riesgo medio",
    "precio": 724.02,
    "shortStrike": 733,
    "longStrike": 734.0,
    "vwap": 718.0,
    "regimen": "Trend Alcista",
    "tramo": "Premarket"
  },
  {
    "timestamp": "2026-06-30 08:36:05",
    "ticker": "QQQ",
    "decision": "esperar confirmación",
    "decisionLabel": "🟡 Esperar confirmación",
    "score": 53.0,
    "semaforo": "🟡 Riesgo medio",
    "precio": 724.02,
    "shortStrike": 733,
    "longStrike": 734.0,
    "vwap": 718.0,
    "regimen": "Trend Alcista",
    "tramo": "Premarket"
  },
  {
    "timestamp": "2026-06-30 09:00:47",
    "decisionLabel": "Entraría",
    "score": 100,
    "precio": 724.08
  },
  {
    "timestamp": "2026-06-30 09:13:10",
    "decisionLabel": "Entraría",
    "score": 100,
    "precio": 724.08
  },
  {
    "timestamp": "2026-06-30 09:21:26",
    "decisionLabel": "Entraría",
    "score": 100,
    "precio": 724.08
  },
  {
    "timestamp": "2026-06-30 10:26:08",
    "decisionLabel": "Entraría",
    "score": 100,
    "precio": 724.08
  },
  {
    "timestamp": "2026-06-30 11:27:36",
    "decisionLabel": "Entraría",
    "score": 100,
    "precio": 724.08
  },
  {
    "timestamp": "2026-06-30 11:35:19",
    "decisionLabel": "Entraría",
    "score": 100,
    "precio": 724.08
  },
  {
    "timestamp": "2026-06-30 11:49:38",
    "decisionLabel": "Entraría",
    "score": 100,
    "precio": 724.08
  },
  {
    "timestamp": "2026-06-30 12:17:56",
    "decisionLabel": "Entraría",
    "score": 100,
    "precio": 724.08
  },
  {
    "timestamp": "2026-06-30 12:30:40",
    "decisionLabel": "Entraría",
    "score": 100,
    "precio": 724.08
  },
  {
    "timestamp": "2026-06-30 12:15:56 UTC",
    "ticker": "QQQ",
    "decision": "esperar confirmación",
    "decisionLabel": "🟡 Esperar confirmación",
    "score": 63.0,
    "semaforo": "🟡 Riesgo medio",
    "precio": 725.21,
    "shortStrike": 734,
    "longStrike": 735.0,
    "vwap": 718.0,
    "regimen": "Rango",
    "tramo": "Premarket"
  },
  {
    "timestamp": "2026-06-30 12:16:49 UTC",
    "ticker": "QQQ",
    "decision": "esperar confirmación",
    "decisionLabel": "🟡 Esperar confirmación",
    "score": 68.0,
    "semaforo": "🟡 Riesgo medio",
    "precio": 725.07,
    "shortStrike": 734,
    "longStrike": 735.0,
    "vwap": 718.0,
    "regimen": "Rango",
    "tramo": "Premarket"
  },
  {
    "timestamp": "2026-06-30 12:20:41 UTC",
    "ticker": "QQQ",
    "decision": "esperar confirmación",
    "decisionLabel": "🟡 Esperar confirmación",
    "score": 68.0,
    "semaforo": "🟡 Riesgo medio",
    "precio": 724.98,
    "shortStrike": 734,
    "longStrike": 735.0,
    "vwap": 718.0,
    "regimen": "Rango",
    "tramo": "Premarket"
  },
  {
    "timestamp": "2026-06-30 12:30:42 UTC",
    "ticker": "QQQ",
    "decision": "esperar confirmación",
    "decisionLabel": "🟡 Esperar confirmación",
    "score": 68.0,
    "semaforo": "🟡 Riesgo medio",
    "precio": 723.89,
    "shortStrike": 732,
    "longStrike": 733.0,
    "vwap": 718.0,
    "regimen": "Rango",
    "tramo": "Premarket"
  },
  {
    "timestamp": "2026-06-30 12:31:29 UTC",
    "ticker": "QQQ",
    "decision": "esperar confirmación",
    "decisionLabel": "🟡 Esperar confirmación",
    "score": 68.0,
    "semaforo": "🟡 Riesgo medio",
    "precio": 723.97,
    "shortStrike": 733,
    "longStrike": 734.0,
    "vwap": 718.0,
    "regimen": "Rango",
    "tramo": "Premarket"
  },
  {
    "timestamp": "2026-06-30 12:40:35 UTC",
    "ticker": "QQQ",
    "decision": "esperar confirmación",
    "decisionLabel": "🟡 Esperar confirmación",
    "score": 68.0,
    "semaforo": "🟡 Riesgo medio",
    "precio": 724.27,
    "shortStrike": 733,
    "longStrike": 734.0,
    "vwap": 718.0,
    "regimen": "Rango",
    "tramo": "Premarket"
  },
  {
    "timestamp": "2026-06-30 12:50:37 UTC",
    "ticker": "QQQ",
    "decision": "esperar confirmación",
    "decisionLabel": "🟡 Esperar confirmación",
    "score": 68.0,
    "semaforo": "🟡 Riesgo medio",
    "precio": 724.07,
    "shortStrike": 733,
    "longStrike": 734.0,
    "vwap": 718.0,
    "regimen": "Rango",
    "tramo": "Premarket"
  },
  {
    "timestamp": "2026-06-30 13:00:52 UTC",
    "ticker": "QQQ",
    "decision": "esperar confirmación",
    "decisionLabel": "🟡 Esperar confirmación",
    "score": 68.0,
    "semaforo": "🟡 Riesgo medio",
    "precio": 723.43,
    "shortStrike": 732,
    "longStrike": 733.0,
    "vwap": 718.0,
    "regimen": "Rango",
    "tramo": "Premarket"
  },
  {
    "timestamp": "2026-06-30 13:10:39 UTC",
    "ticker": "QQQ",
    "decision": "esperar confirmación",
    "decisionLabel": "🟡 Esperar confirmación",
    "score": 68.0,
    "semaforo": "🟡 Riesgo medio",
    "precio": 723.77,
    "shortStrike": 732,
    "longStrike": 733.0,
    "vwap": 718.0,
    "regimen": "Rango",
    "tramo": "Premarket"
  },
  {
    "timestamp": "2026-06-30 13:20:42 UTC",
    "ticker": "QQQ",
    "decision": "esperar confirmación",
    "decisionLabel": "🟡 Esperar confirmación",
    "score": 68.0,
    "semaforo": "🟡 Riesgo medio",
    "precio": 723.55,
    "shortStrike": 732,
    "longStrike": 733.0,
    "vwap": 718.0,
    "regimen": "Rango",
    "tramo": "Premarket"
  },
  {
    "timestamp": "2026-06-30 13:30:51 UTC",
    "ticker": "QQQ",
    "decision": "esperar confirmación",
    "decisionLabel": "🟡 Esperar confirmación",
    "score": 72.0,
    "semaforo": "🟡 Riesgo medio",
    "precio": 725.06,
    "shortStrike": 733,
    "longStrike": 734.0,
    "vwap": null,
    "regimen": "Trend Bajista",
    "tramo": "Apertura"
  },
  {
    "timestamp": "2026-06-30 13:40:43 UTC",
    "ticker": "QQQ",
    "decision": "no entraría",
    "decisionLabel": "🔴 No entraría",
    "score": 69.0,
    "semaforo": "🟡 Riesgo medio",
    "precio": 728.38,
    "shortStrike": 737,
    "longStrike": 738.0,
    "vwap": 726.77,
    "regimen": "Indefinido",
    "tramo": "Apertura"
  },
  {
    "timestamp": "2026-06-30 13:50:36 UTC",
    "ticker": "QQQ",
    "decision": "no entraría",
    "decisionLabel": "🔴 No entraría",
    "score": 75.0,
    "semaforo": "🟢 Riesgo controlado",
    "precio": 728.11,
    "shortStrike": 737,
    "longStrike": 738.0,
    "vwap": 727.14,
    "regimen": "Rango",
    "tramo": "Apertura"
  },
  {
    "timestamp": "2026-07-01 03:30:44",
    "ticker": "QQQ",
    "decision": "no entraría",
    "decisionLabel": "🔴 No entraría",
    "score": 44.0,
    "semaforo": "🔴 Riesgo alto",
    "precio": 736.29,
    "shortStrike": 745,
    "longStrike": 746.0,
    "vwap": 733.95,
    "regimen": "Trend Alcista",
    "tramo": "Premarket"
  },
  {
    "timestamp": "2026-07-01 03:40:38",
    "ticker": "QQQ",
    "decision": "no entraría",
    "decisionLabel": "🔴 No entraría",
    "score": 44.0,
    "semaforo": "🔴 Riesgo alto",
    "precio": 736.29,
    "shortStrike": 745,
    "longStrike": 746.0,
    "vwap": 733.95,
    "regimen": "Trend Alcista",
    "tramo": "Premarket"
  },
  {
    "timestamp": "2026-07-01 04:47:58",
    "ticker": "QQQ",
    "decision": "no entraría",
    "decisionLabel": "🔴 No entraría",
    "score": 52.0,
    "semaforo": "🟡 Riesgo medio",
    "precio": 732.04,
    "shortStrike": 741,
    "longStrike": 742.0,
    "vwap": 733.95,
    "regimen": "Rango",
    "tramo": "Premarket"
  },
  {
    "timestamp": "2026-07-01 04:50:36",
    "ticker": "QQQ",
    "decision": "no entraría",
    "decisionLabel": "🔴 No entraría",
    "score": 52.0,
    "semaforo": "🟡 Riesgo medio",
    "precio": 731.94,
    "shortStrike": 741,
    "longStrike": 742.0,
    "vwap": 733.95,
    "regimen": "Rango",
    "tramo": "Premarket"
  },
  {
    "timestamp": "2026-07-01 09:30:39",
    "ticker": "QQQ",
    "decision": "no entraría",
    "decisionLabel": "🔴 No entraría",
    "score": 62.0,
    "semaforo": "🟡 Riesgo medio",
    "precio": 731.96,
    "shortStrike": 746,
    "longStrike": 747.0,
    "vwap": 733.95,
    "regimen": "Rango",
    "tramo": "Premarket"
  },
  {
    "timestamp": "2026-07-01 09:33:01",
    "ticker": "QQQ",
    "decision": "no entraría",
    "decisionLabel": "🔴 No entraría",
    "score": 62.0,
    "semaforo": "🟡 Riesgo medio",
    "precio": 732.16,
    "shortStrike": 746,
    "longStrike": 747.0,
    "vwap": 733.95,
    "regimen": "Rango",
    "tramo": "Premarket"
  },
  {
    "timestamp": "2026-07-01 09:40:34",
    "ticker": "QQQ",
    "decision": "no entraría",
    "decisionLabel": "🔴 No entraría",
    "score": 62.0,
    "semaforo": "🟡 Riesgo medio",
    "precio": 732.2,
    "shortStrike": 746,
    "longStrike": 747.0,
    "vwap": 733.95,
    "regimen": "Rango",
    "tramo": "Premarket"
  },
  {
    "timestamp": "2026-07-01 09:50:30",
    "ticker": "QQQ",
    "decision": "no entraría",
    "decisionLabel": "🔴 No entraría",
    "score": 62.0,
    "semaforo": "🟡 Riesgo medio",
    "precio": 732.38,
    "shortStrike": 746,
    "longStrike": 747.0,
    "vwap": 733.95,
    "regimen": "Rango",
    "tramo": "Premarket"
  }
]