{
  "ticker": "QQQ",
  "updatedAt": "2026-06-30 13:50:36 UTC",
  "decision": "no entraría",
  "decisionLabel": "🔴 No entraría",
  "decisionTone": "red",
  "score": 75.0,
  "semaforo": "🟢 Riesgo controlado",
  "horaNy": "2026-06-30 09:50",
  "precio": 728.11,
  "precioFuente": "Durante la sesión",
  "shortStrike": 737,
  "longStrike": 738.0,
  "breakeven": 737.1,
  "vwap": 727.14,
  "vwapBias": "Cerca del VWAP",
  "tp": 0.04,
  "stop": 0.2,
  "riesgoMax": 90.0,
  "reasons": [
    {
      "tone": "ok",
      "title": "Cerca del VWAP",
      "text": "Cerca del VWAP"
    },
    {
      "tone": "warn",
      "title": "Apertura: volatilidad inicial alta",
      "text": "Apertura: volatilidad inicial alta (-6)"
    },
    {
      "tone": "warn",
      "title": "Liquidez insuficiente",
      "text": "Liquidez insuficiente (-10)"
    },
    {
      "tone": "ok",
      "title": "Rango favorable para premium",
      "text": "Rango favorable para premium (+3)"
    },
    {
      "tone": "warn",
      "title": "Decisión",
      "text": "Liquidez insuficiente"
    }
  ],
  "alerts": [
    {
      "tone": "warn",
      "title": "Bid-ask amplio en la short call.",
      "text": "Bid-ask amplio en la short call."
    },
    {
      "tone": "warn",
      "title": "Bid-ask amplio en la long call.",
      "text": "Bid-ask amplio en la long call."
    }
  ],
  "context": [
    [
      "Tramo",
      "Apertura"
    ],
    [
      "Régimen",
      "Rango"
    ],
    [
      "Premarket high",
      "$728.30"
    ],
    [
      "Premarket low",
      "$714.67"
    ]
  ],
  "events": [
    [
      "Próximo macro",
      "ISM Manufacturero"
    ],
    [
      "Impacto",
      "Alto"
    ],
    [
      "Mag 7 cercano",
      "N/D"
    ],
    [
      "Días",
      "N/D"
    ]
  ],
  "contextMap": {
    "Tramo": "Apertura",
    "Régimen": "Rango",
    "Premarket high": "$728.30",
    "Premarket low": "$714.67"
  }
}